ellipse.py
lsq_ellipse-2.2.1.dist-info/LICENSE
lsq_ellipse-2.2.1.dist-info/METADATA
lsq_ellipse-2.2.1.dist-info/WHEEL
lsq_ellipse-2.2.1.dist-info/top_level.txt
lsq_ellipse-2.2.1.dist-info/RECORD
