Metadata-Version: 2.1
Name: lsq-ellipse
Version: 2.2.1
Summary: Lease squares fitting of Ellipses
Home-page: https://github.com/bdhammel/least-squares-ellipse-fitting
Author: Ben Hammel
Author-email: bdhammel@gmail.com
License: MIT
Platform: UNKNOWN
License-File: LICENSE
Requires-Dist: numpy
